_audioop.cpython-312-i386-linux-gnu.so
python_audio-0.1.2.dist-info/WHEEL
python_audio-0.1.2.dist-info/RECORD
python_audio-0.1.2.dist-info/top_level.txt
python_audio-0.1.2.dist-info/METADATA
audio/__init__.py
audio/core.py
audio/op.py
