Metadata-Version: 2.4
Name: python-audio
Version: 0.1.2
Summary: Package for working on audio in python
Author-email: Mayank Sinha <sinha.mayank900@gmail.com>
Project-URL: Homepage, https://github.com/AstralScribe/python-audio.git
Project-URL: Issues, https://github.com/AstralScribe/python-audio/issues
Requires-Python: >=3.10
Requires-Dist: setuptools>=42
